setup.py
gp3/__init__.py
gp3.egg-info/PKG-INFO
gp3.egg-info/SOURCES.txt
gp3.egg-info/dependency_links.txt
gp3.egg-info/requires.txt
gp3.egg-info/top_level.txt
gp3/inference/__init__.py
gp3/inference/base.py
gp3/inference/laplace.py
gp3/inference/svi.py
gp3/inference/vanilla.py
gp3/kernels/__init__.py
gp3/kernels/kernels.py
gp3/likelihoods/__init__.py
gp3/likelihoods/likelihoods.py
gp3/utils/__init__.py
gp3/utils/data.py
gp3/utils/optimizers.py
gp3/utils/structure.py
gp3/utils/transforms.py