Metadata-Version: 1.0
Name: gp3
Version: 0.1.3
Summary: Gaussian Processes with Probabilistic Programming
Home-page: https://github.com/as4529/gp3
Author: Anuj Sharma
Author-email: anuj.sharma@columbia.edu
License: UNKNOWN
Platform: UNKNOWN
